<ipxact:component xmlns:ipxact="http://www.accellera.org/XMLSchema/IPXACT/1685-2014" xmlns:xsi="http://www.w3.org/2001/XMLSchema-instance" xsi:schemaLocation="http://www.accellera.org/XMLSchema/IPXACT/1685-2014 http://www.accellera.org/XMLSchema/IPXACT/1685-2014/index.xsd"><ipxact:vendor>example.com</ipxact:vendor><ipxact:library>IP</ipxact:library><ipxact:name>example</ipxact:name><ipxact:version>1.0</ipxact:version><ipxact:memoryMaps><ipxact:memoryMap><ipxact:name>example</ipxact:name><ipxact:addressBlock><ipxact:name>block0</ipxact:name><ipxact:baseAddress>0x0</ipxact:baseAddress><ipxact:range>0x1000</ipxact:range><ipxact:width>32</ipxact:width><ipxact:register><ipxact:name>reg0</ipxact:name><ipxact:addressOffset>0x0</ipxact:addressOffset><ipxact:size>32</ipxact:size><ipxact:field><ipxact:name>field0</ipxact:name><ipxact:description>reg0.field0</ipxact:description><ipxact:bitOffset>0</ipxact:bitOffset><ipxact:bitWidth>32</ipxact:bitWidth><ipxact:access>read-write</ipxact:access><ipxact:resets><ipxact:reset><ipxact:value>0x1234</ipxact:value></ipxact:reset></ipxact:resets></ipxact:field></ipxact:register><ipxact:register><ipxact:name>reg1</ipxact:name><ipxact:addressOffset>0x4</ipxact:addressOffset><ipxact:size>32</ipxact:size><ipxact:field><ipxact:name>field1</ipxact:name><ipxact:description>No Description</ipxact:description><ipxact:bitOffset>16</ipxact:bitOffset><ipxact:bitWidth>8</ipxact:bitWidth><ipxact:access>read-write</ipxact:access><ipxact:resets><ipxact:reset><ipxact:value>0</ipxact:value></ipxact:reset></ipxact:resets></ipxact:field><ipxact:field><ipxact:name>field0</ipxact:name><ipxact:description>No Description</ipxact:description><ipxact:bitOffset>0</ipxact:bitOffset><ipxact:bitWidth>8</ipxact:bitWidth><ipxact:access>read-write</ipxact:access><ipxact:resets><ipxact:reset><ipxact:value>0</ipxact:value></ipxact:reset></ipxact:resets></ipxact:field></ipxact:register><ipxact:register><ipxact:name>reg2</ipxact:name><ipxact:addressOffset>0x8</ipxact:addressOffset><ipxact:size>32</ipxact:size><ipxact:field><ipxact:name>field0</ipxact:name><ipxact:description>No Description</ipxact:description><ipxact:bitOffset>0</ipxact:bitOffset><ipxact:bitWidth>32</ipxact:bitWidth><ipxact:access>read-write</ipxact:access><ipxact:modifiedWriteValue>oneToClear</ipxact:modifiedWriteValue><ipxact:resets><ipxact:reset><ipxact:value>0</ipxact:value></ipxact:reset></ipxact:resets></ipxact:field></ipxact:register><ipxact:register><ipxact:name>reg3</ipxact:name><ipxact:addressOffset>0xc</ipxact:addressOffset><ipxact:size>32</ipxact:size><ipxact:field><ipxact:name>field0</ipxact:name><ipxact:description>No Description</ipxact:description><ipxact:bitOffset>0</ipxact:bitOffset><ipxact:bitWidth>32</ipxact:bitWidth><ipxact:access>read-write</ipxact:access><ipxact:readAction>clear</ipxact:readAction><ipxact:resets><ipxact:reset><ipxact:value>0</ipxact:value></ipxact:reset></ipxact:resets></ipxact:field></ipxact:register><ipxact:register><ipxact:name>rega_0</ipxact:name><ipxact:addressOffset>0x10</ipxact:addressOffset><ipxact:size>32</ipxact:size><ipxact:field><ipxact:name>field0</ipxact:name><ipxact:description>No Description</ipxact:description><ipxact:bitOffset>0</ipxact:bitOffset><ipxact:bitWidth>32</ipxact:bitWidth><ipxact:access>read-write</ipxact:access><ipxact:resets><ipxact:reset><ipxact:value>0</ipxact:value></ipxact:reset></ipxact:resets></ipxact:field></ipxact:register><ipxact:register><ipxact:name>rega_1</ipxact:name><ipxact:addressOffset>0x14</ipxact:addressOffset><ipxact:size>32</ipxact:size><ipxact:field><ipxact:name>field0</ipxact:name><ipxact:description>No Description</ipxact:description><ipxact:bitOffset>0</ipxact:bitOffset><ipxact:bitWidth>32</ipxact:bitWidth><ipxact:access>read-write</ipxact:access><ipxact:resets><ipxact:reset><ipxact:value>0</ipxact:value></ipxact:reset></ipxact:resets></ipxact:field></ipxact:register><ipxact:register><ipxact:name>rega_2</ipxact:name><ipxact:addressOffset>0x18</ipxact:addressOffset><ipxact:size>32</ipxact:size><ipxact:field><ipxact:name>field0</ipxact:name><ipxact:description>No Description</ipxact:description><ipxact:bitOffset>0</ipxact:bitOffset><ipxact:bitWidth>32</ipxact:bitWidth><ipxact:access>read-write</ipxact:access><ipxact:resets><ipxact:reset><ipxact:value>0</ipxact:value></ipxact:reset></ipxact:resets></ipxact:field></ipxact:register><ipxact:register><ipxact:name>regb_0</ipxact:name><ipxact:addressOffset>0x20</ipxact:addressOffset><ipxact:size>32</ipxact:size><ipxact:field><ipxact:name>field1</ipxact:name><ipxact:description>No Description</ipxact:description><ipxact:bitOffset>16</ipxact:bitOffset><ipxact:bitWidth>16</ipxact:bitWidth><ipxact:access>read-write</ipxact:access><ipxact:resets><ipxact:reset><ipxact:value>0</ipxact:value></ipxact:reset></ipxact:resets></ipxact:field><ipxact:field><ipxact:name>field0</ipxact:name><ipxact:description>No Description</ipxact:description><ipxact:bitOffset>0</ipxact:bitOffset><ipxact:bitWidth>16</ipxact:bitWidth><ipxact:access>read-write</ipxact:access><ipxact:resets><ipxact:reset><ipxact:value>0</ipxact:value></ipxact:reset></ipxact:resets></ipxact:field></ipxact:register><ipxact:register><ipxact:name>regb_1</ipxact:name><ipxact:addressOffset>0x24</ipxact:addressOffset><ipxact:size>32</ipxact:size><ipxact:field><ipxact:name>field1</ipxact:name><ipxact:description>No Description</ipxact:description><ipxact:bitOffset>16</ipxact:bitOffset><ipxact:bitWidth>16</ipxact:bitWidth><ipxact:access>read-write</ipxact:access><ipxact:resets><ipxact:reset><ipxact:value>0</ipxact:value></ipxact:reset></ipxact:resets></ipxact:field><ipxact:field><ipxact:name>field0</ipxact:name><ipxact:description>No Description</ipxact:description><ipxact:bitOffset>0</ipxact:bitOffset><ipxact:bitWidth>16</ipxact:bitWidth><ipxact:access>read-write</ipxact:access><ipxact:resets><ipxact:reset><ipxact:value>0</ipxact:value></ipxact:reset></ipxact:resets></ipxact:field></ipxact:register></ipxact:addressBlock><ipxact:addressBlock><ipxact:name>block1</ipxact:name><ipxact:baseAddress>0x1000</ipxact:baseAddress><ipxact:range>0x1000</ipxact:range><ipxact:width>32</ipxact:width><ipxact:register><ipxact:name>reg0</ipxact:name><ipxact:addressOffset>0x0</ipxact:addressOffset><ipxact:size>32</ipxact:size><ipxact:field><ipxact:name>field0</ipxact:name><ipxact:description>No Description</ipxact:description><ipxact:bitOffset>0</ipxact:bitOffset><ipxact:bitWidth>32</ipxact:bitWidth><ipxact:access>read-write</ipxact:access><ipxact:resets><ipxact:reset><ipxact:value>0x1234</ipxact:value></ipxact:reset></ipxact:resets></ipxact:field></ipxact:register><ipxact:register><ipxact:name>reg1</ipxact:name><ipxact:addressOffset>0x4</ipxact:addressOffset><ipxact:size>32</ipxact:size><ipxact:field><ipxact:name>field1</ipxact:name><ipxact:description>No Description</ipxact:description><ipxact:bitOffset>16</ipxact:bitOffset><ipxact:bitWidth>8</ipxact:bitWidth><ipxact:access>read-write</ipxact:access><ipxact:resets><ipxact:reset><ipxact:value>0</ipxact:value></ipxact:reset></ipxact:resets></ipxact:field><ipxact:field><ipxact:name>field0</ipxact:name><ipxact:description>No Description</ipxact:description><ipxact:bitOffset>0</ipxact:bitOffset><ipxact:bitWidth>8</ipxact:bitWidth><ipxact:access>read-write</ipxact:access><ipxact:resets><ipxact:reset><ipxact:value>0</ipxact:value></ipxact:reset></ipxact:resets></ipxact:field></ipxact:register><ipxact:register><ipxact:name>reg2</ipxact:name><ipxact:addressOffset>0x8</ipxact:addressOffset><ipxact:size>32</ipxact:size><ipxact:field><ipxact:name>field0</ipxact:name><ipxact:description>No Description</ipxact:description><ipxact:bitOffset>0</ipxact:bitOffset><ipxact:bitWidth>32</ipxact:bitWidth><ipxact:access>read-write</ipxact:access><ipxact:modifiedWriteValue>oneToClear</ipxact:modifiedWriteValue><ipxact:resets><ipxact:reset><ipxact:value>0</ipxact:value></ipxact:reset></ipxact:resets></ipxact:field></ipxact:register><ipxact:register><ipxact:name>reg3</ipxact:name><ipxact:addressOffset>0xc</ipxact:addressOffset><ipxact:size>32</ipxact:size><ipxact:field><ipxact:name>field0</ipxact:name><ipxact:description>No Description</ipxact:description><ipxact:bitOffset>0</ipxact:bitOffset><ipxact:bitWidth>32</ipxact:bitWidth><ipxact:access>read-write</ipxact:access><ipxact:readAction>clear</ipxact:readAction><ipxact:resets><ipxact:reset><ipxact:value>0</ipxact:value></ipxact:reset></ipxact:resets></ipxact:field></ipxact:register><ipxact:register><ipxact:name>rega_0</ipxact:name><ipxact:addressOffset>0x14</ipxact:addressOffset><ipxact:size>32</ipxact:size><ipxact:field><ipxact:name>field0</ipxact:name><ipxact:description>No Description</ipxact:description><ipxact:bitOffset>0</ipxact:bitOffset><ipxact:bitWidth>32</ipxact:bitWidth><ipxact:access>read-write</ipxact:access><ipxact:resets><ipxact:reset><ipxact:value>0</ipxact:value></ipxact:reset></ipxact:resets></ipxact:field></ipxact:register><ipxact:register><ipxact:name>rega_1</ipxact:name><ipxact:addressOffset>0x18</ipxact:addressOffset><ipxact:size>32</ipxact:size><ipxact:field><ipxact:name>field0</ipxact:name><ipxact:description>No Description</ipxact:description><ipxact:bitOffset>0</ipxact:bitOffset><ipxact:bitWidth>32</ipxact:bitWidth><ipxact:access>read-write</ipxact:access><ipxact:resets><ipxact:reset><ipxact:value>0</ipxact:value></ipxact:reset></ipxact:resets></ipxact:field></ipxact:register><ipxact:register><ipxact:name>regb_0</ipxact:name><ipxact:addressOffset>0x20</ipxact:addressOffset><ipxact:size>32</ipxact:size><ipxact:field><ipxact:name>field1</ipxact:name><ipxact:description>No Description</ipxact:description><ipxact:bitOffset>16</ipxact:bitOffset><ipxact:bitWidth>16</ipxact:bitWidth><ipxact:access>read-write</ipxact:access><ipxact:resets><ipxact:reset><ipxact:value>0</ipxact:value></ipxact:reset></ipxact:resets></ipxact:field><ipxact:field><ipxact:name>field0</ipxact:name><ipxact:description>No Description</ipxact:description><ipxact:bitOffset>0</ipxact:bitOffset><ipxact:bitWidth>16</ipxact:bitWidth><ipxact:access>read-write</ipxact:access><ipxact:resets><ipxact:reset><ipxact:value>0</ipxact:value></ipxact:reset></ipxact:resets></ipxact:field></ipxact:register><ipxact:register><ipxact:name>regb_1</ipxact:name><ipxact:addressOffset>0x24</ipxact:addressOffset><ipxact:size>32</ipxact:size><ipxact:field><ipxact:name>field1</ipxact:name><ipxact:description>No Description</ipxact:description><ipxact:bitOffset>16</ipxact:bitOffset><ipxact:bitWidth>16</ipxact:bitWidth><ipxact:access>read-write</ipxact:access><ipxact:resets><ipxact:reset><ipxact:value>0</ipxact:value></ipxact:reset></ipxact:resets></ipxact:field><ipxact:field><ipxact:name>field0</ipxact:name><ipxact:description>No Description</ipxact:description><ipxact:bitOffset>0</ipxact:bitOffset><ipxact:bitWidth>16</ipxact:bitWidth><ipxact:access>read-write</ipxact:access><ipxact:resets><ipxact:reset><ipxact:value>0</ipxact:value></ipxact:reset></ipxact:resets></ipxact:field></ipxact:register><ipxact:register><ipxact:name>regc_0</ipxact:name><ipxact:addressOffset>0x30</ipxact:addressOffset><ipxact:size>32</ipxact:size><ipxact:field><ipxact:name>field1</ipxact:name><ipxact:description>No Description</ipxact:description><ipxact:bitOffset>16</ipxact:bitOffset><ipxact:bitWidth>16</ipxact:bitWidth><ipxact:access>read-write</ipxact:access><ipxact:resets><ipxact:reset><ipxact:value>0</ipxact:value></ipxact:reset></ipxact:resets></ipxact:field><ipxact:field><ipxact:name>field0</ipxact:name><ipxact:description>No Description</ipxact:description><ipxact:bitOffset>0</ipxact:bitOffset><ipxact:bitWidth>16</ipxact:bitWidth><ipxact:access>read-write</ipxact:access><ipxact:resets><ipxact:reset><ipxact:value>0</ipxact:value></ipxact:reset></ipxact:resets></ipxact:field></ipxact:register><ipxact:register><ipxact:name>regc_1</ipxact:name><ipxact:addressOffset>0x34</ipxact:addressOffset><ipxact:size>32</ipxact:size><ipxact:field><ipxact:name>field1</ipxact:name><ipxact:description>No Description</ipxact:description><ipxact:bitOffset>16</ipxact:bitOffset><ipxact:bitWidth>16</ipxact:bitWidth><ipxact:access>read-write</ipxact:access><ipxact:resets><ipxact:reset><ipxact:value>0</ipxact:value></ipxact:reset></ipxact:resets></ipxact:field><ipxact:field><ipxact:name>field0</ipxact:name><ipxact:description>No Description</ipxact:description><ipxact:bitOffset>0</ipxact:bitOffset><ipxact:bitWidth>16</ipxact:bitWidth><ipxact:access>read-write</ipxact:access><ipxact:resets><ipxact:reset><ipxact:value>0</ipxact:value></ipxact:reset></ipxact:resets></ipxact:field></ipxact:register><ipxact:register><ipxact:name>regc_2</ipxact:name><ipxact:addressOffset>0x38</ipxact:addressOffset><ipxact:size>32</ipxact:size><ipxact:field><ipxact:name>field1</ipxact:name><ipxact:description>No Description</ipxact:description><ipxact:bitOffset>16</ipxact:bitOffset><ipxact:bitWidth>16</ipxact:bitWidth><ipxact:access>read-write</ipxact:access><ipxact:resets><ipxact:reset><ipxact:value>0</ipxact:value></ipxact:reset></ipxact:resets></ipxact:field><ipxact:field><ipxact:name>field0</ipxact:name><ipxact:description>No Description</ipxact:description><ipxact:bitOffset>0</ipxact:bitOffset><ipxact:bitWidth>16</ipxact:bitWidth><ipxact:access>read-write</ipxact:access><ipxact:resets><ipxact:reset><ipxact:value>0</ipxact:value></ipxact:reset></ipxact:resets></ipxact:field></ipxact:register></ipxact:addressBlock></ipxact:memoryMap></ipxact:memoryMaps></ipxact:component>